setup.py
sims_pars/__init__.py
sims_pars/fn.py
sims_pars/monitor.py
sims_pars/prob.py
sims_pars/util.py
sims_pars/bayesnet/__init__.py
sims_pars/bayesnet/bn.py
sims_pars/bayesnet/chromosome.py
sims_pars/bayesnet/dag.py
sims_pars/bayesnet/loci.py
sims_pars/data/__init__.py
sims_pars/data/datafunction.py
sims_pars/data/fn.py
sims_pars/data/frame.py
sims_pars/data/static.py
sims_pars/data/timeseries.py
sims_pars/data/reg/__init__.py
sims_pars/data/reg/glm.py
sims_pars/data/reg/hazard.py
sims_pars/data/reg/lcm.py
sims_pars/data/reg/linear.py
sims_pars/data/reg/survival.py
sims_pars/factory/__init__.py
sims_pars/factory/craftstation.py
sims_pars/fit/__init__.py
sims_pars/fit/base.py
sims_pars/fit/converter.py
sims_pars/fit/results.py
sims_pars/fit/toys.py
sims_pars/fit/abc_smc/__init__.py
sims_pars/fit/abc_smc/alg.py
sims_pars/fit/abcom/__init__.py
sims_pars/fit/abcom/alg.py
sims_pars/fit/ga/__init__.py
sims_pars/fit/ga/alg.py
sims_pars/fit/ga/cross.py
sims_pars/fit/ga/mutate.py
sims_pars/fit/ga/select.py
sims_pars/fit/hme/__init__.py
sims_pars/fit/hme/alg.py
sims_pars/fit/hme/emulator.py
sims_pars/fit/nuts/__init__.py
sims_pars/fit/targets/__init__.py
sims_pars/fit/targets/base.py
sims_pars/fit/targets/multi.py
sims_pars/fit/targets/single.py
sims_pars/fitting/__init__.py
sims_pars/fitting/base.py
sims_pars/fitting/cases.py
sims_pars/fitting/fitter.py
sims_pars/fitting/util.py
sims_pars/simulation/__init__.py
sims_pars/simulation/actor.py
sims_pars/simulation/fn.py
sims_pars/simulation/nodeset.py
sims_pars/simulation/parcore.py
sims_pars/simulation/simucore.py
sims_pars/simulation/simugroup.py
sims_pars-2.6.1.dist-info/LICENSE
sims_pars-2.6.1.dist-info/METADATA
sims_pars-2.6.1.dist-info/WHEEL
sims_pars-2.6.1.dist-info/top_level.txt
sims_pars-2.6.1.dist-info/RECORD
